etracer/__init__.py
etracer/interfaces.py
etracer/models.py
etracer/tracer.py
etracer/utils/__init__.py
etracer/utils/ai_client.py
etracer/utils/cache.py
etracer/utils/printer.py
etracer/utils/spinner.py
etracer/utils/timer.py
etracer-0.1.1.dist-info/licenses/LICENSE
etracer-0.1.1.dist-info/METADATA
etracer-0.1.1.dist-info/WHEEL
etracer-0.1.1.dist-info/top_level.txt
etracer-0.1.1.dist-info/RECORD
